pywhale/PyWhale.py
pywhale/__init__.py
pywhale/api_keys/BTC_demo_key.txt
pywhale/api_keys/BTC_real_key.txt
pywhale/api_keys/DASH_demo_key.txt
pywhale/api_keys/DASH_real_key.txt
pywhale/api_keys/ETH_real_key.txt
pywhale/api_keys/LTC_real_key.txt
pywhale/plugins/__init__.py
pywhale/plugins/connection/Api.py
pywhale/plugins/connection/__init__.py
pywhale/plugins/trade/General.py
pywhale/plugins/trade/Live.py
pywhale/plugins/trade/Turbo.py
pywhale/plugins/trade/__init__.py
pywhale-0.7.dist-info/METADATA
pywhale-0.7.dist-info/RECORD
pywhale-0.7.dist-info/WHEEL
pywhale-0.7.dist-info/top_level.txt
